README.rst
setup.py
lxd/__init__.py
lxd/client.py
lxd/exceptions.py
lxd/transport.py
lxd/utils.py
lxd/version.py
lxd.egg-info/PKG-INFO
lxd.egg-info/SOURCES.txt
lxd.egg-info/dependency_links.txt
lxd.egg-info/requires.txt
lxd.egg-info/top_level.txt
lxd/endpoints/__init__.py
lxd/endpoints/base.py
lxd/endpoints/certificates.py
lxd/endpoints/instances.py
lxd/endpoints/operations.py
lxd/endpoints/server.py
lxd/entities/__init__.py
lxd/entities/base.py
lxd/entities/certificates.py
lxd/entities/instances.py
lxd/entities/operations.py
lxd/entities/response.py
lxd/entities/server.py