Metadata-Version: 2.1
Name: lxd
Version: 0.2.16
Summary: LXD Client
Home-page: UNKNOWN
Author: Alexander Vasin <alvassin@yandex-team.ru>
Author-email: alvassin@yandex-team.ru
License: MIT
Project-URL: Source, https://github.com/alvassin/lxd
Platform: all
Classifier: Intended Audience :: Developers
Classifier: Natural Language :: Russian
Classifier: Operating System :: MacOS
Classifier: Operating System :: POSIX
Classifier: Development Status :: 3 - Alpha
Classifier: Programming Language :: Python
Classifier: Programming Language :: Python :: 3
Classifier: Programming Language :: Python :: 3.10
Classifier: Programming Language :: Python :: Implementation :: CPython
Requires-Python: >=3.10
Provides-Extra: dev
